LICENSE
README.md
setup.py
discord_menu.egg-info/PKG-INFO
discord_menu.egg-info/SOURCES.txt
discord_menu.egg-info/dependency_links.txt
discord_menu.egg-info/top_level.txt
discordmenu/__init__.py
discordmenu/discord_client.py
discordmenu/intra_message_state.py
discordmenu/reaction_filter.py
discordmenu/embed/__init__.py
discordmenu/embed/base.py
discordmenu/embed/components.py
discordmenu/embed/emoji.py
discordmenu/embed/menu.py
discordmenu/embed/text.py
discordmenu/embed/transitions.py
discordmenu/embed/view.py
discordmenu/embed/view_state.py
discordmenu/embed/wrapper.py
discordmenu/emoji/__init__.py
discordmenu/emoji/emoji.py
discordmenu/emoji/emoji_cache.py
discordmenu/menu/__init__.py
discordmenu/menu/base.py
discordmenu/menu/closable_menu.py
discordmenu/menu/footer.py
discordmenu/menu/scrollable_menu.py
discordmenu/menu/simple_tabbed_text_menu.py
discordmenu/menu/simple_text_menu.py
discordmenu/menu/tabbed_menu.py
discordmenu/menu/listener/__init__.py
discordmenu/menu/listener/bot_protocol.py
discordmenu/menu/listener/errors.py
discordmenu/menu/listener/menu_listener.py
discordmenu/menu/listener/menu_map.py
discordmenu/menu/listener/reaction_filter_list.py
test/__init__.py
test/testcog/__init__.py
test/testcog/main.py
test/testcog/examples/__init__.py
test/testcog/examples/closable_menu.py
test/testcog/examples/rich_text_menu.py
test/testcog/examples/scrollable_menu.py
test/testcog/examples/tabbed_menu.py