Metadata-Version: 2.1
Name: discord-menu
Version: 0.16.16
Summary: A library to create tabbed menus in Discord messages
Home-page: https://github.com/TsubakiBotPad/discord-menu
Author: The Tsubotki Team
Author-email: 69992611+TsubakiBotPad@users.noreply.github.com
License: Apache-2.0 License
Classifier: Programming Language :: Python :: 3
Classifier: Operating System :: OS Independent
Requires-Python: >=3.10
License-File: LICENSE
